tinscan/LASTZ_wrapper.py
tinscan/__init__.py
tinscan/_version.py
tinscan/run_align.py
tinscan/run_prep.py
tinscan/run_scan.py
tinscan-0.2.1.dist-info/METADATA
tinscan-0.2.1.dist-info/WHEEL
tinscan-0.2.1.dist-info/entry_points.txt
tinscan-0.2.1.dist-info/licenses/LICENSE
tinscan-0.2.1.dist-info/RECORD
