Metadata-Version: 2.3
Name: tinscan
Version: 0.2.1
Summary: Find alignment signatures characteristic of transposon insertion sites.
Project-URL: homepage, https://github.com/adamtaranto/TE-insertion-scanner
Project-URL: documentation, https://github.com/adamtaranto/TE-insertion-scanner
Project-URL: repository, https://github.com/adamtaranto/TE-insertion-scanner
Author-email: Adam Taranto <adam.p.taranto@gmail.com>
License: MIT
License-File: LICENSE
Classifier: Intended Audience :: Science/Research
Classifier: License :: OSI Approved :: MIT License
Classifier: Programming Language :: Python :: 3
Classifier: Topic :: Scientific/Engineering :: Bio-Informatics
Requires-Python: >=3.8
Requires-Dist: biopython>=1.70
Provides-Extra: tests
Requires-Dist: pytest; extra == 'tests'
